billing/__init__.py
billing/exceptions.py
billing/http.py
billing/schemas.py
billing/activities/__init__.py
billing/activities/schemas.py
billing/keys/__init__.py
billing/keys/schemas.py
hkjx_billing_sdk-0.2.7.dist-info/METADATA
hkjx_billing_sdk-0.2.7.dist-info/WHEEL
hkjx_billing_sdk-0.2.7.dist-info/licenses/LICENSE
hkjx_billing_sdk-0.2.7.dist-info/RECORD
