Metadata-Version: 2.4
Name: hkjx-billing-sdk
Version: 0.2.7
Summary: Huakunjingxiu Billing SDK
Project-URL: Homepage, https://github.com/a1huakunjingxiu/billing-sdk
Project-URL: Bug Tracker, https://github.com/a1huakunjingxiu/billing-sdk/issues
Author-email: A1 Huakunjingxiu <dev@a1huakunjingxiu.com>
License: MIT
License-File: LICENSE
Classifier: License :: OSI Approved :: MIT License
Classifier: Operating System :: OS Independent
Classifier: Programming Language :: Python :: 3
Requires-Python: >=3.12
Requires-Dist: curlify2>=2.0.0
Requires-Dist: dotenv>=0.9.9
Requires-Dist: httpx>=0.28.1
Requires-Dist: pydantic>=2.10.6
Provides-Extra: dev
Requires-Dist: pre-commit>=3.7.0; extra == 'dev'
Requires-Dist: pytest-asyncio>=0.22.0; extra == 'dev'
Requires-Dist: pytest-mock>=3.14.0; extra == 'dev'
Requires-Dist: pytest>=6.0; extra == 'dev'
Requires-Dist: ruff>=0.0.254; extra == 'dev'
